{
  "肉類係數": {
    "1": [
      "大肉",
      "烤大肉",
      "大肉乾",
      "怪獸肉",
      "烤怪獸肉",
      "烤怪獸肉乾"
    ],
    "0.5": [
      "小肉",
      "烤小肉",
      "小肉乾",
      "雞腿",
      "烤雞腿",
      "蛙腿",
      "烤蛙腿",
      "魚",
      "烤魚",
      "鰻魚",
      "烤鰻魚"
    ]
  },
  "蔬菜類係數": {
    "1": [
      "玉米",
      "烤玉米",
      "胡蘿蔔",
      "烤胡蘿蔔",
      "南瓜",
      "烤瓜",
      "茄子",
      "烤茄子",
      "仙人掌肉",
      "烤仙人掌肉",
      "仙人掌花"
    ],
    "0.5": [
      "紅蘑菇",
      "烤紅蘑菇",
      "綠蘑菇",
      "烤綠蘑菇",
      "藍蘑菇",
      "烤藍蘑菇"
    ]
  },
  "水果類係數": {
    "1": [
      "番石榴",
      "烤番石榴",
      "榴槤",
      "烤榴槤",
      "火龍果",
      "烤火龍果",
      "香蕉",
      "烤香蕉",
      "西瓜",
      "烤西瓜"
    ],
    "0.5": [
      "漿果",
      "烤漿果"
    ]
  },
  "蛋類係數": {
    "1": [
      "雞蛋",
      "烤雞蛋"
    ],
    "4": [
      "高腳鳥蛋",
      "烤高腳鳥蛋"
    ]
  }
}